scikit_neutrosophic/__init__.py
scikit_neutrosophic/neutrosophic_knn.py
scikit_neutrosophic/neutrosophic_linear_regression.py
scikit_neutrosophic/neutrosophic_svm.py
scikit_neutrosophic-0.0.1.dist-info/METADATA
scikit_neutrosophic-0.0.1.dist-info/WHEEL
scikit_neutrosophic-0.0.1.dist-info/top_level.txt
scikit_neutrosophic-0.0.1.dist-info/RECORD
