Metadata-Version: 2.1
Name: scikit-neutrosophic
Version: 0.0.1
Summary: Neutrosophic Machine Learning Algorithms
Home-page: https://github.com/GyanendraChaubey/scikit-neutrosophic
Author: Gyanendra Chaubey
Author-email: gyanendrachaubey68@gmail.com
Classifier: Development Status :: 3 - Alpha
Classifier: Intended Audience :: Developers
Classifier: Intended Audience :: Science/Research
Classifier: License :: OSI Approved :: MIT License
Classifier: Programming Language :: Python :: 3
Classifier: Programming Language :: Python :: 3.6
Classifier: Programming Language :: Python :: 3.7
Classifier: Programming Language :: Python :: 3.8
Classifier: Programming Language :: Python :: 3.9
Classifier: Topic :: Software Development :: Libraries :: Python Modules
Requires-Python: >=3.6
Requires-Dist: numpy
Requires-Dist: scipy
Requires-Dist: scikit-learn
